pmlib/__init__.py
pmlib/cli.py
pmlib/task.py
tests/test_pmlib.py
pmlib-1.1.2.dist-info/LICENSE
pmlib-1.1.2.dist-info/METADATA
pmlib-1.1.2.dist-info/WHEEL
pmlib-1.1.2.dist-info/RECORD
