Metadata-Version: 2.1
Name: pmlib
Version: 1.1.2
Summary: Manage projects via CLI
License: BSD-3-Clause
Keywords: project,management
Author: Mike Pennington
Author-email: mike@pennington.net
Maintainer: Mike Pennington
Maintainer-email: mike@pennington.net
Requires-Python: >=3.9,<4.0.0
Classifier: Development Status :: 5 - Production/Stable
Classifier: Environment :: Plugins
Classifier: Intended Audience :: Developers
Classifier: Intended Audience :: Information Technology
Classifier: Intended Audience :: System Administrators
Classifier: Intended Audience :: Telecommunications Industry
Classifier: License :: OSI Approved :: BSD License
Classifier: License :: OSI Approved :: GNU General Public License (GPL)
Classifier: License :: OSI Approved :: GNU General Public License v3 (GPLv3)
Classifier: Natural Language :: English
Classifier: Operating System :: OS Independent
Classifier: Programming Language :: Python
Classifier: Programming Language :: Python :: 3
Classifier: Programming Language :: Python :: 3.9
Classifier: Programming Language :: Python :: 3.10
Classifier: Programming Language :: Python :: 3.11
Classifier: Programming Language :: Python :: 3.12
Requires-Dist: attrs (==23.2.0)
Requires-Dist: email-validator (==2.1.0.post1)
Requires-Dist: loguru (==0.7.2)
Requires-Dist: matplotlib (==3.8.2)
Requires-Dist: pandas (==2.1.4)
Requires-Dist: tasklib (==2.5.1)
Requires-Dist: texttable (==1.7.0)
Project-URL: homepage, https://github.com/mpenning/pmlib
Project-URL: repository, https://github.com/mpenning/pmlib
Project-URL: source, https://github.com/mpenning/pmlib
